consoleiotools/__init__.py
consoleiotools/__main__.py
consoleiotools-5.0.1.dist-info/LICENSE
consoleiotools-5.0.1.dist-info/METADATA
consoleiotools-5.0.1.dist-info/WHEEL
consoleiotools-5.0.1.dist-info/top_level.txt
consoleiotools-5.0.1.dist-info/RECORD
