Metadata-Version: 2.2
Name: consoleiotools
Version: 5.0.1
Summary: Console tools for inputs and outputs in Python
Author-email: Kyan <kai@kyan001.com>
License: The MIT License (MIT)
Project-URL: Homepage, https://github.com/kyan001/PyConsoleIOTools
Project-URL: Issue Tracker, https://github.com/kyan001/PyConsoleIOTools/issues
Project-URL: Source Code, https://github.com/kyan001/PyConsoleIOTools
Keywords: python,console,input,output,tool
Classifier: Development Status :: 5 - Production/Stable
Classifier: Intended Audience :: Developers
Classifier: Topic :: Software Development :: User Interfaces
Classifier: License :: OSI Approved :: MIT License
Classifier: Programming Language :: Python :: 3
Classifier: Programming Language :: Python :: 3 :: Only
Requires-Python: >=3.6
License-File: LICENSE
Requires-Dist: rich
Provides-Extra: dev
